{
  "paragraphs": [
    {
      "text": "%md\n## hello world",
      "user": "admin",
      "dateUpdated": "2018-09-30 09:36:10.166",
      "config": {
        "colWidth": 12.0,
        "fontSize": 9.0,
        "enabled": true,
        "results": {},
        "editorSetting": {
          "editOnDblClick": true,
          "completionSupport": false,
          "language": "markdown"
        },
        "editorMode": "ace/mode/markdown",
        "editorHide": true,
        "tableHide": false
      },
      "settings": {
        "params": {},
        "forms": {}
      },
      "results": {
        "code": "SUCCESS",
        "msg": [
          {
            "type": "HTML",
            "data": "\u003cdiv class\u003d\"markdown-body\"\u003e\n\u003ch2\u003ehello world\u003c/h2\u003e\n\u003c/div\u003e"
          }
        ]
      },
      "apps": [],
      "jobName": "paragraph_1538300156355_-1782786097",
      "id": "20180930-093556_1673691594",
      "dateCreated": "2018-09-30 09:35:56.355",
      "dateStarted": "2018-09-30 09:36:10.203",
      "dateFinished": "2018-09-30 09:36:12.669",
      "status": "FINISHED",
      "progressUpdateIntervalMs": 500
    },
    {
      "text": "%md\n",
      "user": "admin",
      "dateUpdated": "2018-09-30 09:36:10.104",
      "config": {},
      "settings": {
        "params": {},
        "forms": {}
      },
      "apps": [],
      "jobName": "paragraph_1538300170100_354712597",
      "id": "20180930-093610_112830622",
      "dateCreated": "2018-09-30 09:36:10.100",
      "status": "READY",
      "progressUpdateIntervalMs": 500
    }
  ],
  "name": "test",
  "id": "2DUAU6N8A",
  "noteParams": {},
  "noteForms": {},
  "angularObjects": {
    "md:shared_process": [],
    "angular:shared_process": []
  },
  "config": {
    "isZeppelinNotebookCronEnable": false
  },
  "info": {}
}